License.txt
MANIFEST.in
README.md
RUNME.py
packaging.txt
requirements.txt
setup.py
vicksbase/__init__.py
vicksbase/async_fb.py
vicksbase/decorators.py
vicksbase/firebase.py
vicksbase/firebase_token_generator.py
vicksbase/jsonutil.py
vicksbase/lazy.py
vicksuploader/__init__.py
vicksuploader/github.py
vicksuploader/morse.py
vicksuploader/playfair.py
vicksuploader/pypi.py
vicksuploader/vixtor.py
vixuploader.egg-info/PKG-INFO
vixuploader.egg-info/SOURCES.txt
vixuploader.egg-info/dependency_links.txt
vixuploader.egg-info/top_level.txt